printerm/README.md
printerm/__init__.py
printerm/error_handling.py
printerm/exceptions.py
printerm/utils.py
printerm/interfaces/__init__.py
printerm/interfaces/cli.py
printerm/interfaces/web.py
printerm/interfaces/gui/__init__.py
printerm/interfaces/gui/main.py
printerm/interfaces/gui/settings.py
printerm/interfaces/gui/theme.py
printerm/interfaces/gui/widgets/__init__.py
printerm/interfaces/gui/widgets/base.py
printerm/interfaces/gui/widgets/dialog.py
printerm/interfaces/gui/widgets/main_window.py
printerm/interfaces/web_templates/base.html
printerm/interfaces/web_templates/index.html
printerm/interfaces/web_templates/print_template.html
printerm/interfaces/web_templates/settings.html
printerm/interfaces/web_templates/static/icons/printer_icon_16.png
printerm/interfaces/web_templates/static/icons/printer_icon_32.png
printerm/interfaces/web_templates/static/icons/printer_icon_96.png
printerm/services/__init__.py
printerm/services/config_service.py
printerm/services/interfaces.py
printerm/services/markdown_renderer.py
printerm/services/printer_service.py
printerm/services/template_service.py
printerm/services/update_service.py
printerm/templates/__init__.py
printerm/templates/print_templates/README.md
printerm/templates/print_templates/agenda.yaml
printerm/templates/print_templates/small_note.yaml
printerm/templates/print_templates/task.yaml
printerm/templates/print_templates/ticket.yaml
printerm/templates/scripts/README.md
printerm/templates/scripts/__init__.py
printerm/templates/scripts/agenda_generator.py
printerm/templates/scripts/base.py
printerm/templates/scripts/script_loader.py
printerm/templates/scripts/script_registry.py
printerm-1.3.1.dist-info/METADATA
printerm-1.3.1.dist-info/WHEEL
printerm-1.3.1.dist-info/entry_points.txt
printerm-1.3.1.dist-info/licenses/LICENSE
printerm-1.3.1.dist-info/RECORD
