Metadata-Version: 2.4
Name: printerm
Version: 1.3.1
Summary: Thermal printer printing tool
Author-email: Mikołaj Kaczmarek <12432719+AN0DA@users.noreply.github.com>
License: MIT
License-File: LICENSE
Requires-Python: >=3.13
Requires-Dist: click>=8.2.1
Requires-Dist: flask>=3.1.0
Requires-Dist: mistune>=3.1.2
Requires-Dist: packaging>=25.0
Requires-Dist: platformdirs>=4.3.7
Requires-Dist: python-escpos[win32]>=3.0.0
Requires-Dist: requests>=2.32.3
Requires-Dist: typer>=0.15.2
Requires-Dist: unidecode>=1.3.8
Requires-Dist: waitress>=3.0.2
